{
  "$schema": "http://json.schemastore.org/template",
  "author": "KAL",
  "classifications": [ "SP-Dev", "Console" ],
  "identity": "KAL.XFS4IoT.SP-Dev.Framework.Templates.CashRecycler",
  "groupIdentity": "KAL.XFS4IoT.SP-Dev.Framework.Templates.CashRecycler",
  "name": "KAL-SP-Dev CashRecycler Template",
  "shortName": "spdev-Car",
  "sourceName": "CashRecyclerTemplate",
  "tags": {
    "language": "C#",
    "type": "project"
  },
  "description": "CashRecycler Template",
  "defaultName": "CashRecycler1",
  "precedence": 6000
}